ner_tool/__init__.py
ner_tool/get_metrics.py
ner_tool/ner.py
ner_tool-0.3.dist-info/METADATA
ner_tool-0.3.dist-info/WHEEL
ner_tool-0.3.dist-info/top_level.txt
ner_tool-0.3.dist-info/RECORD
